tox_nuitka/__init__.py
tox_nuitka/plugin.py
tox_nuitka-0.0.1.dist-info/METADATA
tox_nuitka-0.0.1.dist-info/RECORD
tox_nuitka-0.0.1.dist-info/WHEEL
tox_nuitka-0.0.1.dist-info/entry_points.txt
tox_nuitka-0.0.1.dist-info/top_level.txt
